dsk_server/__init__.py
dsk_server/dsk_server.py
dsk_server/dsk_utils.py
dsk_server-0.1.8.dist-info/METADATA
dsk_server-0.1.8.dist-info/WHEEL
dsk_server-0.1.8.dist-info/entry_points.txt
dsk_server-0.1.8.dist-info/licenses/LICENSE
dsk_server-0.1.8.dist-info/RECORD
