Metadata-Version: 2.1
Name: dsk-server
Version: 0.1.8
Summary: Distribution server for files stored in DSK format image file.
License-File: LICENSE
Requires-Python: >=3.8
Requires-Dist: construct>=2.10.70
Requires-Dist: fastapi>=0.104.1
Requires-Dist: fire>=0.5.0
Requires-Dist: uvicorn>=0.24.0.post1
